Workbook

Sheet Venue Level Data
A1: TAIV BARS AND RESTAURANTS
A2: ClientID | B2: Venue | C2: Venue Type | D2: Market | E2: State | F2: Impressions | G2: Plays | H2: ScreensAtLocation
A3: -NKyY24mM7F_24N1CBGP | B3: Beaver Bar | C3: =VLOOKUP(A3,Sheet2!A:C, 3, FALSE) -> Entertainment|Bars | D3: Phoenix | E3: =VLOOKUP(A3,Sheet2!A:E, 5, FALSE) -> AZ | F3: 17910.878 | G3: 406 | H3: 3
A4: -NN3_Fzj4OfkOLwT7YiX | B4: Divided Vine | C4: =VLOOKUP(A4,Sheet2!A:C, 3, FALSE) -> Entertainment|Bars | D4: Phoenix | E4: =VLOOKUP(A4,Sheet2!A:E, 5, FALSE) -> AZ | F4: 987.72817 | G4: 286 | H4: 2
A5: -Nor7k92yNrGjV5uogb3 | B5: Yo Pauly's Pizza | C5: =VLOOKUP(A5,Sheet2!A:C, 3, FALSE) -> Entertainment|Casual Dining | D5: Phoenix | E5: =VLOOKUP(A5,Sheet2!A:E, 5, FALSE) -> AZ | F5: 6089.1418 | G5: 424 | H5: 4
A6: -Nt3-7ndpSvJdtT87yiG | B6: Tavern Grille Scottsdale | C6: =VLOOKUP(A6,Sheet2!A:C, 3, FALSE) -> Entertainment|Casual Dining | D6: Phoenix | E6: =VLOOKUP(A6,Sheet2!A:E, 5, FALSE) -> AZ | F6: 13505.13 | G6: 272 | H6: 2
A7: -NvhXU3G_ByXt1osJ2sk | B7: Pour Decisions Patio & Kitchen | C7: =VLOOKUP(A7,Sheet2!A:C, 3, FALSE) -> Entertainment|Casual Dining | D7: Phoenix | E7: =VLOOKUP(A7,Sheet2!A:E, 5, FALSE) -> AZ | F7: 2158.564 | G7: 179 | H7: 2
A8: -NoxZXEHFb3dPADRKlx- | B8: Lil Capo Pizzeria - Westgate | C8: =VLOOKUP(A8,Sheet2!A:C, 3, FALSE) -> Entertainment|Casual Dining | D8: Phoenix | E8: =VLOOKUP(A8,Sheet2!A:E, 5, FALSE) -> AZ | F8: 6066.1774 | G8: 339 | H8: 2
A9: -O-mf2jWNsnUBHVHaBDn | B9: University Sports Grill | C9: =VLOOKUP(A9,Sheet2!A:C, 3, FALSE) -> Entertainment|Casual Dining | D9: Phoenix | E9: =VLOOKUP(A9,Sheet2!A:E, 5, FALSE) -> AZ | F9: 7084.421 | G9: 239 | H9: 4
A10: -NzA-WIXsqac5doheXDi | B10: The rib shop | C10: =VLOOKUP(A10,Sheet2!A:C, 3, FALSE) -> Entertainment|Bars | D10: Phoenix | E10: =VLOOKUP(A10,Sheet2!A:E, 5, FALSE) -> AZ | F10: 2621.8756 | G10: 448 | H10: 4
A11: -NoIx1qE9Nsqosy8x0GR | B11: IL Capo Pizzeria | C11: =VLOOKUP(A11,Sheet2!A:C, 3, FALSE) -> Entertainment|Casual Dining | D11: Phoenix | E11: =VLOOKUP(A11,Sheet2!A:E, 5, FALSE) -> AZ | F11: 2218.8967 | G11: 124 | H11: 2
A12: -NtwoHKumPGrfpO1LZgS | B12: Batchelor's Pad BBQ | C12: =VLOOKUP(A12,Sheet2!A:C, 3, FALSE) -> Entertainment|Casual Dining | D12: Phoenix | E12: =VLOOKUP(A12,Sheet2!A:E, 5, FALSE) -> AZ | F12: 1642.1973 | G12: 216 | H12: 2
A13: -O5KQsxzHNOf0LbXnvtR | B13: Union Grill and Tap | C13: =VLOOKUP(A13,Sheet2!A:C, 3, FALSE) -> Entertainment|Casual Dining | D13: Phoenix | E13: =VLOOKUP(A13,Sheet2!A:E, 5, FALSE) -> AZ | F13: 12070.742 | G13: 394 | H13: 4
A14: -NLNqoKPZaMyk66ucxUR | B14: Metro Sports Bar and Billiards | C14: =VLOOKUP(A14,Sheet2!A:C, 3, FALSE) -> Entertainment|Bars | D14: Phoenix | E14: =VLOOKUP(A14,Sheet2!A:E, 5, FALSE) -> AZ | F14: 39914.303 | G14: 1640 | H14: 16
... A137: -OJVc-aSS-ywMDJ3PWs0 | B137: Scotland Yard - The Pub | C137: =VLOOKUP(A137,Sheet2!A:C, 3, FALSE) -> Entertainment|Bars | D137: San Diego | E137: =VLOOKUP(A137,Sheet2!A:E, 5, FALSE) -> CA | F137: 1538.9123 | G137: 86 | H137: 2
A138: -O4vKUnAFcZgZPrmFDss | B138: Red Pepper Taqueria - Dunwoody | C138: =VLOOKUP(A138,Sheet2!A:C, 3, FALSE) -> Entertainment|Casual Dining | D138: Atlanta | E138: FL | F138: 9376.6282 | G138: 524 | H138: 4
A139: -O5sQuxBEF-KjSyzE38g | B139: Hogg Daddy's | C139: =VLOOKUP(A139,Sheet2!A:C, 3, FALSE) -> Entertainment|Bars | D139: Tampa Bay | E139: =VLOOKUP(A139,Sheet2!A:E, 5, FALSE) -> FL | F139: 7336.6747 | G139: 410 | H139: 4
A140: -Mek9YBX0kvGE5Di7oqG | B140: Big Dog Station | C140: =VLOOKUP(A140,Sheet2!A:C, 3, FALSE) -> Entertainment|Casual Dining | D140: Miami | E140: =VLOOKUP(A140,Sheet2!A:E, 5, FALSE) -> FL | F140: 10921.566 | G140: 525 | H140: 3
A141: -Mx4rSl3yiwwqCW0XijQ | B141: Birdie's Pub | C141: =VLOOKUP(A141,Sheet2!A:C, 3, FALSE) -> Entertainment|Bars | D141: Tampa Bay | E141: =VLOOKUP(A141,Sheet2!A:E, 5, FALSE) -> FL | F141: 5821.0232 | G141: 492 | H141: 4
A142: -NxxWAf2h3mbnHD6YxvX | B142: Machupicchu Peruvian Cuisine | C142: =VLOOKUP(A142,Sheet2!A:C, 3, FALSE) -> Entertainment|Casual Dining | D142: Miami | E142: =VLOOKUP(A142,Sheet2!A:E, 5, FALSE) -> FL | F142: 1067.9236 | G142: 421 | H142: 2
A143: -O6gmH5bhhdlACXbfHpw | B143: The Chill Room Lake Worth Beach | C143: =VLOOKUP(A143,Sheet2!A:C, 3, FALSE) -> Retail|Dispensaries | D143: Miami | E143: =VLOOKUP(A143,Sheet2!A:E, 5, FALSE) -> FL | F143: 4580.9481 | G143: 256 | H143: 1
A144: -MrEYhB038IikhW11S5- | B144: Even Keel Fish Shack | C144: =VLOOKUP(A144,Sheet2!A:C, 3, FALSE) -> Entertainment|Casual Dining | D144: Miami | E144: =VLOOKUP(A144,Sheet2!A:E, 5, FALSE) -> FL | F144: 1875.4078 | G144: 694 | H144: 4
A145: -NAtTAcu34_4uRnzBTSa | B145: The Par Pub | C145: =VLOOKUP(A145,Sheet2!A:C, 3, FALSE) -> Entertainment|Bars | D145: Tampa Bay | E145: =VLOOKUP(A145,Sheet2!A:E, 5, FALSE) -> FL | F145: 4090.087 | G145: 441 | H145: 2
A146: -OJPo573jcRAGSbaLZgN | B146: Play By Play Sports Bar and Grill | C146: =VLOOKUP(A146,Sheet2!A:C, 3, FALSE) -> Entertainment|Casual Dining | D146: Miami | E146: =VLOOKUP(A146,Sheet2!A:E, 5, FALSE) -> FL | F146: 14375.038 | G146: 645 | H146: 4
A147: -MZww_GNQba-ycEVf6gy | B147: Temple Street Eatery | C147: =VLOOKUP(A147,Sheet2!A:C, 3, FALSE) -> Entertainment|Casual Dining | D147: Miami | E147: =VLOOKUP(A147,Sheet2!A:E, 5, FALSE) -> FL | F147: 8984.1332 | G147: 423 | H147: 2
A148: -NyRmpnENv71dY1zdMGC | B148: The Kenwood | C148: =VLOOKUP(A148,Sheet2!A:C, 3, FALSE) -> Entertainment|Bars | D148: Tampa Bay | E148: =VLOOKUP(A148,Sheet2!A:E, 5, FALSE) -> FL | F148: 6397.3093 | G148: 541 | H148: 5
A149: -Nm6dZN5fLR5oHiO35Ra | B149: Autentica Taqueria | C149: =VLOOKUP(A149,Sheet2!A:C, 3, FALSE) -> Entertainment|Casual Dining | D149: Miami | E149: =VLOOKUP(A149,Sheet2!A:E, 5, FALSE) -> FL | F149: 1370.1974 | G149: 485 | H149: 2
A150: -Me68kpYuJvSn-sGCagD | B150: Mis-Cue Lounge | C150: =VLOOKUP(A150,Sheet2!A:C, 3, FALSE) -> Entertainment|Bars | D150: Miami | E150: =VLOOKUP(A150,Sheet2!A:E, 5, FALSE) -> FL | F150: 18503.494 | G150: 446 | H150: 3
... A178: -Mq1WI0CJ2m5kUSp8dAV | B178: Papa’s Raw Bar | C178: =VLOOKUP(A178,Sheet2!A:C, 3, FALSE) -> Entertainment|Casual Dining | D178: Miami | E178: =VLOOKUP(A178,Sheet2!A:E, 5, FALSE) -> FL | F178: 42443.663 | G178: 802 | H178: 3
A179: -OaenoaeVQiceQ82880v | B179: Tootsie's Cabaret Miami | C179: =VLOOKUP(A179,Sheet2!A:C, 3, FALSE) -> #N/A | D179: Miami | E179: FL | F179: 7068.2598 | G179: 395 | H179: 3
A180: -OVK0EsyRITkzszoYTP6 | B180: Wicked Cantina - Sarasota (Downtown) | C180: =VLOOKUP(A180,Sheet2!A:C, 3, FALSE) -> Entertainment|Casual Dining | D180: Tampa Bay | E180: =VLOOKUP(A180,Sheet2!A:E, 5, FALSE) -> FL | F180: 11470.265 | G180: 641 | H180: 5
A181: -NN8gjonmznHbkKA37nB | B181: Cotee River Brewing Company | C181: =VLOOKUP(A181,Sheet2!A:C, 3, FALSE) -> Entertainment|Bars | D181: Tampa Bay | E181: =VLOOKUP(A181,Sheet2!A:E, 5, FALSE) -> FL | F181: 5724.1409 | G181: 305 | H181: 2
A182: -MrOD9UGCxMw0Flu5Tkt | B182: Ray’s Hideaway | C182: =VLOOKUP(A182,Sheet2!A:C, 3, FALSE) -> Entertainment|Casual Dining | D182: Miami | E182: =VLOOKUP(A182,Sheet2!A:E, 5, FALSE) -> FL | F182: 11265.378 | G182: 503 | H182: 5
A183: -NSpyBluUYWj-2npe69o | B183: OLLIES ON THE BEACH | C183: =VLOOKUP(A183,Sheet2!A:C, 3, FALSE) -> Entertainment|Casual Dining | D183: Tampa Bay | E183: =VLOOKUP(A183,Sheet2!A:E, 5, FALSE) -> FL | F183: 1968.8191 | G183: 618 | H183: 4
A184: -OSuKhhtpMuav1FiT0ze | B184: Beef 'O' Brady's - Lakewood Ranch | C184: =VLOOKUP(A184,Sheet2!A:C, 3, FALSE) -> Entertainment|Casual Dining | D184: Tampa Bay | E184: =VLOOKUP(A184,Sheet2!A:E, 5, FALSE) -> FL | F184: 13098.649 | G184: 732 | H184: 5
A185: -NWmaaeVbFYIxOJ1ZCPk | B185: Frenchy's South Beach Cafe | C185: =VLOOKUP(A185,Sheet2!A:C, 3, FALSE) -> Entertainment|Casual Dining | D185: Tampa Bay | E185: =VLOOKUP(A185,Sheet2!A:E, 5, FALSE) -> FL | F185: 8207.4885 | G185: 301 | H185: 2
A186: -N4E0J9JgupmCllp_avl | B186: Sculley's | C186: =VLOOKUP(A186,Sheet2!A:C, 3, FALSE) -> Entertainment|Casual Dining | D186: Tampa Bay | E186: =VLOOKUP(A186,Sheet2!A:E, 5, FALSE) -> FL | F186: 6172.2592 | G186: 440 | H186: 3
A187: -OMN4c6SJnIHy85GllBb | B187: Wicked Cantina - Bradenton Beach | C187: =VLOOKUP(A187,Sheet2!A:C, 3, FALSE) -> Entertainment|Casual Dining | D187: Tampa Bay | E187: =VLOOKUP(A187,Sheet2!A:E, 5, FALSE) -> FL | F187: 5113.9737 | G187: 459 | H187: 4
A188: -N6il_guoHS36867z0lM | B188: Bar 23fifty | C188: =VLOOKUP(A188,Sheet2!A:C, 3, FALSE) -> Entertainment|Casual Dining | D188: Tampa Bay | E188: =VLOOKUP(A188,Sheet2!A:E, 5, FALSE) -> FL | F188: 1517.5486 | G188: 299 | H188: 3
A189: -ONVOUUXNLvazHrXVn8R | B189: Scoreboard Social | C189: =VLOOKUP(A189,Sheet2!A:C, 3, FALSE) -> Entertainment|Casual Dining | D189: Other | E189: =VLOOKUP(A189,Sheet2!A:E, 5, FALSE) -> FL | F189: 6692.4789 | G189: 374 | H189: 3
A190: -N6xaPMHScKkUEeIhKEw | B190: Boar and Buffalo Craft Bar | C190: =VLOOKUP(A190,Sheet2!A:C, 3, FALSE) -> Entertainment|Bars | D190: Tampa Bay | E190: =VLOOKUP(A190,Sheet2!A:E, 5, FALSE) -> FL | F190: 1546.9006 | G190: 161 | H190: 2
A191: -OSyh5GKOAiM9KyXfs2N | B191: Stones Throw | C191: =VLOOKUP(A191,Sheet2!A:C, 3, FALSE) -> Entertainment|Casual Dining | D191: Other | E191: =VLOOKUP(A191,Sheet2!A:E, 5, FALSE) -> FL | F191: 5225.1439 | G191: 292 | H191: 4
... A198: -MuS5YBkIspHgsgDH9hJ | B198: The Big Cheese | C198: =VLOOKUP(A198,Sheet2!A:C, 3, FALSE) -> Entertainment|Casual Dining | D198: Miami | E198: =VLOOKUP(A198,Sheet2!A:E, 5, FALSE) -> FL | F198: 2952.4695 | G198: 217 | H198: 2
A199: -Oaely1UaGiAMVf9CHVO | B199: Cheetah Hallandale Beach | C199: =VLOOKUP(A199,Sheet2!A:C, 3, FALSE) -> #N/A | D199: Miami | E199: FL | F199: 6334.5923 | G199: 354 | H199: 3
A200: -O6gmX8F3xds4WLgx6aO | B200: The Chill Room - Pinellas Park | C200: =VLOOKUP(A200,Sheet2!A:C, 3, FALSE) -> Retail|Dispensaries | D200: Tampa Bay | E200: =VLOOKUP(A200,Sheet2!A:E, 5, FALSE) -> FL | F200: 3095.7188 | G200: 173 | H200: 1
A201: -MrE_75uUoVWDZcTDb6S | B201: Mona's | C201: =VLOOKUP(A201,Sheet2!A:C, 3, FALSE) -> Entertainment|Bars | D201: Miami | E201: =VLOOKUP(A201,Sheet2!A:E, 5, FALSE) -> FL | F201: 1266.6895 | G201: 234 | H201: 1
A202: -NxNismlfPsQivJq0JT_ | B202: The Drunken Clam | C202: =VLOOKUP(A202,Sheet2!A:C, 3, FALSE) -> Entertainment|Casual Dining | D202: Tampa Bay | E202: =VLOOKUP(A202,Sheet2!A:E, 5, FALSE) -> FL | F202: 23804.759 | G202: 328 | H202: 4
A203: -ODwlzE1T_da7xo_y_zG | B203: Black Bear Golf Club | C203: =VLOOKUP(A203,Sheet2!A:C, 3, FALSE) -> Entertainment|Sports Entertainment | D203: Other | E203: =VLOOKUP(A203,Sheet2!A:E, 5, FALSE) -> FL | F203: 1971.3832 | G203: 88 | H203: 2
A204: -NqYL8XPM7wVuPEI_kd0 | B204: Clear Sky Draught Haus | C204: =VLOOKUP(A204,Sheet2!A:C, 3, FALSE) -> Entertainment|Casual Dining | D204: Tampa Bay | E204: =VLOOKUP(A204,Sheet2!A:E, 5, FALSE) -> FL | F204: 11618.666 | G204: 220 | H204: 2
A205: -N92xUdJjmhnqAmhtLQ4 | B205: Jimbos Pit Bar B-Q | C205: =VLOOKUP(A205,Sheet2!A:C, 3, FALSE) -> Entertainment|Casual Dining | D205: Tampa Bay | E205: =VLOOKUP(A205,Sheet2!A:E, 5, FALSE) -> FL | F205: 581.81649 | G205: 89 | H205: 3
A206: -Muvzh54bIKQpQAfPRwH | B206: Deck 84 | C206: =VLOOKUP(A206,Sheet2!A:C, 3, FALSE) -> Entertainment|Casual Dining | D206: Miami | E206: =VLOOKUP(A206,Sheet2!A:E, 5, FALSE) -> FL | F206: 5287.026 | G206: 171 | H206: 4
A207: -NCQ0npKABw2smiS5RW9 | B207: Burt & Max’s | C207: =VLOOKUP(A207,Sheet2!A:C, 3, FALSE) -> Entertainment|Casual Dining | D207: Miami | E207: =VLOOKUP(A207,Sheet2!A:E, 5, FALSE) -> FL | F207: 14940.625 | G207: 283 | H207: 4
A208: -Nzd8DQ6VeioOEg5EVs9 | B208: Sneaky's Sports Bar & Grill | C208: =VLOOKUP(A208,Sheet2!A:C, 3, FALSE) -> Entertainment|Casual Dining | D208: Tampa Bay | E208: =VLOOKUP(A208,Sheet2!A:E, 5, FALSE) -> FL | F208: 5457.7702 | G208: 305 | H208: 2
A209: -OTY2gGlhc46GJaTam-j | B209: Stinger's Bar & Grill | C209: =VLOOKUP(A209,Sheet2!A:C, 3, FALSE) -> Entertainment|Casual Dining | D209: Miami | E209: =VLOOKUP(A209,Sheet2!A:E, 5, FALSE) -> FL | F209: 16641.726 | G209: 930 | H209: 5
A210: -Mx4tO0nXYe2jl0rSg4t | B210: Twisted Tiki | C210: =VLOOKUP(A210,Sheet2!A:C, 3, FALSE) -> Entertainment|Casual Dining | D210: Tampa Bay | E210: =VLOOKUP(A210,Sheet2!A:E, 5, FALSE) -> FL | F210: 8467.208 | G210: 246 | H210: 2
A211: -OQ4XhiNKqR9Z-PglHiS | B211: Igot's Martiki Bar | C211: =VLOOKUP(A211,Sheet2!A:C, 3, FALSE) -> Entertainment|Bars | D211: Miami | E211: =VLOOKUP(A211,Sheet2!A:E, 5, FALSE) -> FL | F211: 6048.2831 | G211: 338 | H211: 3
... A439: -NEM-tMm9msxQhCa2TUy | B439: Honey's Place | C439: =VLOOKUP(A439,Sheet2!A:C, 3, FALSE) -> Entertainment|Casual Dining | D439: San Antonio | E439: =VLOOKUP(A439,Sheet2!A:E, 5, FALSE) -> TX | F439: 35.455766 | G439: 8 | H439: 2
A441: TAIV RETAIL
A442: clientId | B442: venue | C442: venue type | D442: market | E442: state | F442: impressions | G442: plays | H442: ScreensAtLocation
A443: -O4vh6kJenm6CowzNEvT | B443: Super Saver Express, 900 20th St, Phenix City | C443: =VLOOKUP(A443,[1]Sheet2!A:C, 3, FALSE) -> Retail|Convenience Stores | D443: Other | E443: =VLOOKUP(A443,[1]Sheet2!A:E, 5, FALSE) -> AL | F443: 469614 | G443: 47725 | H443: 3
A444: -OSUa-zq_IAm1t4nzLSt | B444: Shop24 Chevron - Saraland - 617 Celeste Rd | C444: =VLOOKUP(A444,[1]Sheet2!A:C, 3, FALSE) -> Retail|Convenience Stores | D444: Other | E444: =VLOOKUP(A444,[1]Sheet2!A:E, 5, FALSE) -> AL | F444: 63021 | G444: 15005 | H444: 1
A445: -OJykuRPLLBucBE0UoLA | B445: Mini Mart Food Store - 3312 Pepperell Pkwy #6029 | C445: =VLOOKUP(A445,[1]Sheet2!A:C, 3, FALSE) -> Retail|Convenience Stores | D445: Other | E445: =VLOOKUP(A445,[1]Sheet2!A:E, 5, FALSE) -> AL | F445: 19126.8 | G445: 8855 | H445: 1
A446: -ODvgLlnJE2XsJC0Ei7N | B446: Royal Package Store - Montgomery (5761 Woodmere Blvd) | C446: =VLOOKUP(A446,[1]Sheet2!A:C, 3, FALSE) -> Retail|Liquor Stores | D446: Other | E446: =VLOOKUP(A446,[1]Sheet2!A:E, 5, FALSE) -> AL | F446: 17187 | G446: 17187 | H446: 2
A447: -OB7UCQznmkg1Lpr3VVq | B447: Marathon, 1283 Center Point Pkwy, Birmingham, AL | C447: =VLOOKUP(A447,[1]Sheet2!A:C, 3, FALSE) -> Retail|Convenience Stores | D447: Other | E447: =VLOOKUP(A447,[1]Sheet2!A:E, 5, FALSE) -> AL | F447: 195151.89 | G447: 44519 | H447: 3
A448: -OJ09bRsIalxvz1IzIhH | B448: All American Beverage - 421 N Broad St #1727 | C448: =VLOOKUP(A448,[1]Sheet2!A:C, 3, FALSE) -> Retail|Liquor Stores | D448: Other | E448: =VLOOKUP(A448,[1]Sheet2!A:E, 5, FALSE) -> AL | F448: 102780 | G448: 10278 | H448: 1
A449: -OJTuw2IUP1ax0o3jI0w | B449: Cherokee Food Shop - 947 Cherokee Road | C449: =VLOOKUP(A449,[1]Sheet2!A:C, 3, FALSE) -> Retail|Convenience Stores | D449: Other | E449: =VLOOKUP(A449,[1]Sheet2!A:E, 5, FALSE) -> AL | F449: 146600 | G449: 14660 | H449: 1
A450: -ODvghsInExUkKUnCwf3 | B450: Perry Hill Package Store (1113 Perry Hill Road) | C450: =VLOOKUP(A450,[1]Sheet2!A:C, 3, FALSE) -> Retail|Convenience Stores | D450: Other | E450: =VLOOKUP(A450,[1]Sheet2!A:E, 5, FALSE) -> AL | F450: 34226.3 | G450: 14881 | H450: 2
A451: -OJ-kN0gZg9ruWwYNFn3 | B451: Juna Smoke Shop 24/7 - 4910 South 12th Av | C451: =VLOOKUP(A451,[1]Sheet2!A:C, 3, FALSE) -> Retail|Dispensaries | D451: Other | E451: =VLOOKUP(A451,[1]Sheet2!A:E, 5, FALSE) -> AZ | F451: 70961.38 | G451: 18242 | H451: 1
A452: -OJ-pASLsvqIndR3E8MT | B452: Marana Smoke Shop - 11851 W Marana Rd Unit A | C452: =VLOOKUP(A452,[1]Sheet2!A:C, 3, FALSE) -> Retail|Dispensaries | D452: Other | E452: =VLOOKUP(A452,[1]Sheet2!A:E, 5, FALSE) -> AZ | F452: 42865.2 | G452: 19845 | H452: 3
A453: -OM9-YKCA177wd32_PnL | B453: Pyramid Smoke Shop & Mini Market - 2130 Apache Trail | C453: =VLOOKUP(A453,[1]Sheet2!A:C, 3, FALSE) -> Retail|Dispensaries | D453: Phoenix | E453: =VLOOKUP(A453,[1]Sheet2!A:E, 5, FALSE) -> AZ | F453: 62236.47 | G453: 29219 | H453: 2
A454: -OJ-rKdWIibaHctPRqLr | B454: Olive Market - 9009 North 103rd Av | C454: =VLOOKUP(A454,[1]Sheet2!A:C, 3, FALSE) -> Retail|Convenience Stores | D454: Phoenix | E454: =VLOOKUP(A454,[1]Sheet2!A:E, 5, FALSE) -> AZ | F454: 29733.16 | G454: 13894 | H454: 1
... A868: -OJ0TReqnbXGRGDiMr85 | B868: CBD American Shaman - Portage | C868: =VLOOKUP(A868,[1]Sheet2!A:C, 3, FALSE) -> Retail|Dispensaries | D868: Other | E868: =VLOOKUP(A868,[1]Sheet2!A:E, 5, FALSE) -> WI | F868: 4644.5 | G868: 1327 | H868: 1

Sheet State Level Data
A1: TAIV BARS AND RESTAURANTS
A2: state | B2: impressions | C2: plays | D2: spend
A3: AZ | B3: 259631.52 | C3: 10766 | D3: 2596.32
A4: CA | B4: 723713.96 | C4: 40374 | D4: 7737.14
A5: FL | B5: 833498.58 | C5: 37184 | D5: 8334.99
A6: GA | B6: 268212.78 | C6: 12650 | D6: 2622.13
A7: IL | B7: 406065.21 | C7: 15599 | D7: 4560.65
A8: TX | B8: 944701.25 | C8: 41844 | D8: 9947.25
A9: Total | B9: =SUM(B3:B8) -> 3435823.3 | C9: =SUM(C3:C8) -> 158417 | D9: 35798.38
A11: TAIV RETAIL
A13: state | B13: impressions | C13: plays | D13: spend
A14: AL | B14: 1047707 | C14: 173110 | D14: 368.16
A15: AZ | B15: 959682.53 | C15: 209671 | D15: 499.65
A16: CA | B16: 3375977.3 | C16: 869479 | D16: 1761.93
A17: DC | B17: 206858.41 | C17: 40894 | D17: 78.89
A18: DE | B18: 547354.5 | C18: 84128 | D18: 210.38
A19: FL | B19: 3218573.5 | C19: 849659 | D19: 1893.42
A20: GA | B20: 1537669.6 | C20: 593462 | D20: 1183.38
A21: ID | B21: 10547.26 | C21: 6718 | D21: 52.59
A22: IL | B22: 2158186.9 | C22: 630141 | D22: 1367.47
A23: MN | B23: 552694.34 | C23: 132231 | D23: 315.57
A24: MO | B24: 708491.82 | C24: 209179 | D24: 394.46
A25: MS | B25: 386977.19 | C25: 90113 | D25: 157.78
... A35: WI | B35: 1716854.2 | C35: 420098 | D35: 867.82
A36: total | B36: =SUM(B14:B35) -> 26841066 | C36: =SUM(C14:C35) -> 7200462 | D36: 15384

Sheet Creative Level Data
A1: TAIV BARS AND RESTAURANTS
A2: SlideId | B2: SlideName | C2: ImageName | D2: Impressions | E2: Plays
A3: -OYrg9wHWxhr1xQxArVJ | B3: Betonline - August Ncaa Ad.mp4 | C3: 1756502316530-Betonline - August Ncaa Ad.mp4 | D3: 270544.85 | E3: 11623
A4: -Ob4m-EbQs8mu_fqwfC2 | B4: Justin herbert - BO AD.mp4 | C4: 1759959978415-Justin herbert - BO AD.mp4 | D4: 1115230.8 | E4: 52196
A5: -Ob4m4_tjIaOwngh7j8g | B5: Justin herbert - BO AD.mp4 | C5: 1759960001567-Justin herbert - BO AD.mp4 | D5: 312824.14 | E5: 14243
A6: -OcBpRtGjyR0gomk9Dw3 | B6: NBA_WK43_Betonline.mp4 | C6: 1761151924886-NBA_WK43_Betonline.mp4 | D6: 1141994.6 | E6: 54495
A7: -OcLrNw8q7xOschyCGYK | B7: Oct24_MLB.mp4 | C7: 1761320205347-Oct24_MLB.mp4 | D7: 50031.053 | E7: 2430
A8: -Oe2SWhz1Oyd0Ufz_DQS | B8: BetOnline Temp.mp4 | C8: 1763142230983-BetOnline Temp.mp4 | D8: 396955.77 | E8: 17969
A9: -OewcZVPYNZ3TRByIr7C | B9: Untitled design (2).mp4 | C9: 1764101500393-Untitled design (2).mp4 | D9: 148242.01 | E9: 5461
A11: TAIV RETAIL
A12: slideId | B12: slideName | C12: imageName | D12: impressions | E12: plays
A13: -OYr_M4Gqrx5eTdGGAON | B13: Betonline - August Ncaa Ad.mp4 | C13: 1756500528025-Betonline - August Ncaa Ad.mp4 | D13: 37710.24 | E13: 10493
A14: -OZskSDeS434sK4w16hP | B14: BetOnline - NFL (DALLASSF)..mp4 | C14: 1757593950113-BetOnline - NFL (DALLASSF)..mp4 | D14: 8.54 | E14: 2
A15: -Oa0NwAhG8iWxgizsg3v | B15: Copy of BetOnline - NFL (DALLASSF)..mp4 | C15: 1758812528255-Copy of BetOnline - NFL (DALLASSF)..mp4 | D15: 21557.27 | E15: 6370
A16: -Oauw_dhjlDqBy-VVrYK | B16: Justin herbert - BO AD.mp4 | C16: 1759778201590-Justin herbert - BO AD.mp4 | D16: 26145869 | E16: 7010211
A17: -Ob4oFBtP6mXXLKlVJZw | B17: Justin herbert - BO AD.mp4 | C17: 1759960570991-Justin herbert - BO AD.mp4 | D17: 16903.4 | E17: 4861
A18: -Ob4oHGiK6VFMdJfuCO5 | B18: Justin herbert - BO AD.mp4 | C18: 1759960579657-Justin herbert - BO AD.mp4 | D18: 16484.03 | E18: 4626
A19: -Ob4oJII28aMgiWTRogc | B19: Justin herbert - BO AD.mp4 | C19: 1759960587921-Justin herbert - BO AD.mp4 | D19: 16378.55 | E19: 4641
A20: -Ob4oXNY2JbC_TYAuN_C | B20: Justin herbert - BO AD.mp4 | C20: 1759960645421-Justin herbert - BO AD.mp4 | D20: 16188.71 | E20: 4617
A21: -Ob4oZUpQPOEXwgHi2Lw | B21: Justin herbert - BO AD.mp4 | C21: 1759960653786-Justin herbert - BO AD.mp4 | D21: 41723.85 | E21: 11502
A22: -Ob4ogkC4tjsmu-4yCSJ | B22: BetOnline - MLB(OCT).mp4 | C22: 1759960661373-BetOnline - MLB(OCT).mp4 | D22: 16437.74 | E22: 4612
A23: -Ob4onZxLd8AzmYolkLi | B23: Justin herbert - BO AD.mp4 | C23: 1759960715573-Justin herbert - BO AD.mp4 | D23: 16099.04 | E23: 4614
A24: -OcBqC5aXielx9xFB5NR | B24: NBA_WK43_Betonline.mp4 | C24: 1761152122631-NBA_WK43_Betonline.mp4 | D24: 417349.07 | E24: 112187
... A27: -OewcfMgBEYwxwSpP1kU | B27: Untitled design (2).mp4 | C27: 1764101512032-Untitled design (2).mp4 | D27: 15512.54 | E27: 4223

Sheet Spend By Day
A1: TAIV BARS AND RESTAURANTS
A2: Date | B2: Impressions | C2: Plays | D2: Spend
A3: 45962 | B3: 103917.79 | C3: 5154 | D3: 1167
A4: 45963 | B4: 85337.978 | C4: 4215 | D4: 1167
A5: 45964 | B5: 117633.48 | C5: 5700 | D5: 535
A6: 45965 | B6: 108871.32 | C6: 5443 | D6: 535
A7: 45966 | B7: 60596.608 | C7: 2981 | D7: 535
A8: 45967 | B8: 122856.85 | C8: 5925 | D8: 1707
A9: 45968 | B9: 138060.62 | C9: 6792 | D9: 1707
A10: 45969 | B10: 137786.79 | C10: 6701 | D10: 1707
A11: 45970 | B11: 104650.32 | C11: 5109 | D11: 1707
A12: 45971 | B12: 85850.706 | C12: 4167 | D12: 535.18
A13: 45972 | B13: 49515.898 | C13: 2432 | D13: 535
A14: 45973 | B14: 54046.188 | C14: 2568 | D14: 535
... A28: 45987 | B28: 70072.591 | C28: 2769 | D28: 116.67
A29: 45988 | B29: 162366.76 | C29: 4846 | D29: 1586.666 | F29: .
A30: 45989 | B30: 206020.23 | C30: 7133 | D30: 1586.666
A31: 45990 | B31: 180267.68 | C31: 7372 | D31: 1586.666
A32: 45991 | B32: 165715.3 | C32: 7324 | D32: 1586.666
A33: Total | B33: =SUM(B3:B32) -> 3435823.3 | C33: =SUM(C3:C32) -> 158417 | D33: =SUM(D3:D32) -> 35798.41
A35: TAIV RETAIL
A37: date | B37: impressions | C37: plays | D37: spend
A38: 45962 | B38: 1769195.7 | C38: 475125 | D38: 690
A39: 45963 | B39: 1554101.9 | C39: 421242 | D39: 690
A40: 45964 | B40: 1893941.2 | C40: 507144 | D40: 247
A41: 45965 | B41: 597768.59 | C41: 161495 | D41: 247
A42: 45966 | B42: 226666.79 | C42: 58975 | D42: 247
A43: 45967 | B43: 1543242.7 | C43: 413816 | D43: 690
A44: 45968 | B44: 1911580.9 | C44: 515665 | D44: 690
A45: 45969 | B45: 1869106.6 | C45: 504929 | D45: 690
A46: 45970 | B46: 1688881 | C46: 456005 | D46: 690
A47: 45971 | B47: 1925531 | C47: 512707 | D47: 247
A48: 45972 | B48: 809525.43 | C48: 216926 | D48: 247
A49: 45973 | B49: 377395.68 | C49: 99051 | D49: 247
... A67: 45991 | B67: 69343.05 | C67: 18548 | D67: 690
A68: total | B68: =SUM(B38:B67) -> 26841066 | C68: =SUM(C38:C67) -> 7200462 | D68: =SUM(D38:D67) -> 15384

Sheet Sheet2
A1: Firebase Id | B1: IAB Venue Type | C1: Vistar Venue Type | D1: Account Name | E1: Shipping State/Province | F1: Account ID | G1: Revenue Share Percentage | H1: DMA
A2: -Lm89I_2XS4Taz6KQV7u | B2: Entertainment | Restaurant and Bar | C2: Entertainment|Casual Dining | D2: Fionns Grant Park | E2: MB | F2: 001OG000016zOVF | G2: 15 | H2: WINNIPEG
A3: -N7vB4glPqShJ1qEHZau | B3: Entertainment | Restaurant and Bar | C3: Entertainment|Bars | D3: Taiv HQ | E3: TX | F3: 0018V00002RiBln | G3: 15 | H3: SAN ANTONIO
A4: -NVfdTVT2B7L9M4DW-uK | B4: Entertainment | Restaurant and Bar | C4: Entertainment|Casual Dining | D4: Paddy Kelly's | E4: MA | F4: 001OG000019i3Xb | G4: 15 | H4: BOSTON (MANCHESTER)
A5: -O9M57k5rIUKvFdpgX4O | B5: Entertainment | Restaurant and Bar | C5: Entertainment|Casual Dining | D5: Horus Cafe | E5: NY | F5: 0018V00002f5kWa | G5: 15 | H5: NEW YORK
A6: -O9WJ2SlG98VV_CKfYaP | B6: Entertainment | Restaurant and Bar | C6: Entertainment|Casual Dining | D6: Shotzee's Bar And Grill | E6: TX | F6: 0018V00002hB8TI | G6: 15 | H6: DALLAS - FT. WORTH
A7: -O_CyzMLiCsHEy0Fka16 | B7: Entertainment | Restaurant and Bar | C7: Entertainment|Casual Dining | D7: Wonder Bar | E7: NJ | F7: 001OG000016yDuO | G7: 15 | H7: PHILADELPHIA
A8: -O_Czs_45eSb_6t3Phb5 | B8: Entertainment | Restaurant and Bar | C8: Entertainment|Casual Dining | D8: Dooney's Pub Voorhees | E8: NJ | F8: 001OG000018R0na | G8: 15 | H8: PHILADELPHIA
A9: -O_D-Sxw48a26HdIwQug | B9: Entertainment | Restaurant and Bar | C9: Entertainment|Casual Dining | D9: Dooney's Pub Delran | E9: NJ | F9: 001OG000018Qt99 | G9: 15 | H9: PHILADELPHIA
A10: -O_D1YnHKYI4O12HfWo- | B10: Entertainment | Restaurant and Bar | C10: Entertainment|Casual Dining | D10: Patrizia's Taverna | E10: NY | F10: 001OG000017J7yw | G10: 15 | H10: NEW YORK
A11: -O_Ddul1kBg8t-1ZI3CW | B11: Entertainment | Restaurant and Bar | C11: Entertainment|Casual Dining | D11: Pikes Cinema Bar and Grill | E11: MD | F11: 001OG000016ueKm | G11: 15 | H11: BALTIMORE
A12: -O_DgPsRfCybGjUKPONk | B12: Entertainment | Restaurant and Bar | C12: Entertainment|Bars | D12: Del Webb Lakewood Ranch Lake House | E12: FL | F12: 001OG000018YsSH | G12: 15 | H12: TAMPA - ST. PETE (SARASOTA)
A13: -O_DgSV0jE3wCUe-w7W3 | B13: Entertainment | Restaurant and Bar | C13: Entertainment|Casual Dining | D13: Element Restaurant & Bar | E13: NJ | F13: 001OG000018R0KE | G13: 15 | H13: NEW YORK
... A125: -ObY8tmwM7Ao_GTe8Q3v | B125: Entertainment | Restaurant and Bar | C125: Entertainment|Casual Dining | D125: Cagney's | E125: MA | F125: 001OG000010cAvU | G125: 15 | H125: BOSTON (MANCHESTER)
A126: -ObYYBUZCzBcK8jRU-CW | B126: Entertainment | Restaurant and Bar | C126: Entertainment|Casual Dining | D126: Shell Shack HO | E126: TX | F126: 001OG00001Abv4H | H126: DALLAS - FT. WORTH
A127: -ObZ29cn65HHsRWuOGVN | B127: Entertainment | Restaurant and Bar | C127: Entertainment|Casual Dining | D127: Village Tavern | Bar & grill | E127: MA | F127: 001OG000010c6bW | G127: 15 | H127: BOSTON (MANCHESTER)
A128: -ObZJLWbRo16k9hzWNvD | B128: Entertainment | Restaurant and Bar | C128: Entertainment|Bars | D128: Water's Edge Bar & Grill | E128: MO | F128: 001OG000019l7yB | G128: 15 | H128: KANSAS CITY
A129: -ObZK1Kr4KB3y8z3PA2o | B129: Entertainment | Restaurant and Bar | C129: Entertainment|Bars | D129: Edge on 7 Bar & Grill | E129: MO | F129: 001OG000019lKVY | G129: 15 | H129: KANSAS CITY
A130: -Oc1v_L4RIPb3uzdQmCZ | B130: Entertainment | Restaurant and Bar | C130: Entertainment|Casual Dining | D130: Hermosa Brewing Company - Hermosa Beach | E130: CA | F130: 001OG00000uoXWl | G130: 15 | H130: LOS ANGELES
A131: -Oc1yXXkafD_XW1CiDyA | B131: Entertainment | Restaurant and Bar | C131: Entertainment|Casual Dining | D131: Hermosa Brewing Company Torrance | E131: CA | F131: 001OG00000uoP0m | G131: 15 | H131: LOS ANGELES
A132: -Oc2J1u8VZRIs_sQaFcA | B132: Entertainment | Restaurant and Bar | C132: Entertainment|Bars | D132: Olde Town Tavern and Grill | E132: CO | F132: 001OG000019lLro | G132: 15 | H132: DENVER
A133: -Oc6d7Dzz-k3Yy3FMOyH | B133: Entertainment | Restaurant and Bar | C133: Entertainment|Bars | D133: The Bar West Plaza | E133: MO | F133: 001OG000019lK4J | G133: 15 | H133: KANSAS CITY
A134: -Oc7Cb5Ig_MFr74FCduV | B134: Entertainment | Restaurant and Bar | C134: Entertainment|Casual Dining | D134: Orangedale Lounge | E134: AZ | F134: 001OG00001AJCOz | G134: 15 | H134: PHOENIX (PRESCOTT)
A135: -Oc7PkVYWXh1T5-OHyTK | B135: Entertainment | Restaurant and Bar | C135: Entertainment|Casual Dining | D135: Turtle Bay | E135: LA | F135: 001OG0000181s1H | G135: 15 | H135: NEW ORLEANS
A136: -OcbaSd8n289b4TF6bwi | B136: Entertainment | Restaurant and Bar | C136: Entertainment|Casual Dining | D136: Hook & Reel Cajun Seafood & Bar - Denver | E136: CO | F136: 001OG00001ARP5i | G136: 15 | H136: DENVER
A137: -OcBcyjKzkR0o3scyAOw | B137: Entertainment | Restaurant and Bar | C137: Entertainment|Casual Dining | D137: Ott's Greentop | E137: NJ | F137: 001OG000018QyGl | G137: 15 | H137: PHILADELPHIA
A138: -OcBdoq0GN-c4bKBuS1h | B138: Entertainment | Restaurant and Bar | C138: Entertainment|Casual Dining | D138: Braddock's Tavern | E138: NJ | F138: 001OG000018Qt96 | G138: 15 | H138: PHILADELPHIA
... A147: -OckiVL3ZeUAhqdHptyI | B147: Entertainment | Restaurant and Bar | C147: Entertainment|Casual Dining | D147: PlayMakers Sports Bar & Grill | E147: MO | F147: 001OG00001AGYQQ | G147: 15 | H147: ST. LOUIS
A148: -OckkHIwHwesl_Alpw5g | B148: Entertainment | Restaurant and Bar | C148: Entertainment|Casual Dining | D148: Drake's Paddock Shops | E148: KY | F148: 001OG00001ANxsM | H148: LOUISVILLE
A149: -OckqNFu8a3f2wm3tfi5 | B149: Entertainment | Restaurant and Bar | C149: Entertainment|Casual Dining | D149: Timber Creek Grill | E149: MO | F149: 001OG00001AGdME | G149: 15 | H149: ST. LOUIS
A150: -OckZnznwPETT83dXyxq | B150: Entertainment | Restaurant and Bar | C150: Entertainment|Bars | D150: Gibsons Bar & Steakhouse (Rosemont) | E150: IL | F150: 0018V00002fiUTi | G150: 15 | H150: CHICAGO
A151: -Ocl3YURzB3hqWpNCihW | B151: Entertainment | Restaurant and Bar | C151: Entertainment|Casual Dining | D151: Oskar Blues Grill & Brew - Colorado Springs | E151: CO | F151: 001OG00001B4w8E | G151: 15 | H151: COLORADO SPRINGS - PUEBLO
A152: -OclfIL7DihFnUotOLl- | B152: Entertainment | Restaurant and Bar | C152: Entertainment|Casual Dining | D152: The Rally Sports Bar & Grille | E152: RI | F152: 001OG00001B5Kgn | G152: 15 | H152: PROVIDENCE - NEW BEDFORD
A153: -OclfiT7G9-yMrOuFRe3 | B153: Entertainment | Restaurant and Bar | C153: Entertainment|Casual Dining | D153: O'Rourkes Bar & Grill | E153: RI | F153: 001OG00001B5LmX | G153: 15 | H153: PROVIDENCE - NEW BEDFORD
A154: -OclIv76luGq0F9mIcjN | B154: Entertainment | Restaurant and Bar | C154: Entertainment|Casual Dining | D154: 1356 Public House | E154: MO | F154: 001OG00001AGc6R | G154: 15 | H154: ST. LOUIS
A155: -OcllBz-_Oq2RcqRRPJ1 | B155: Entertainment | Restaurant and Bar | C155: Entertainment|Casual Dining | D155: Birch & Bay Roofdeck Coastal Kitchen | E155: RI | F155: 001OG00001B5Hr0 | G155: 15 | H155: PROVIDENCE - NEW BEDFORD
A156: -Oclp0GbFp15zpdGNvHe | B156: Entertainment | Restaurant and Bar | C156: Entertainment|Casual Dining | D156: Locales Taco + Tequila Bar | E156: CO | F156: 001OG00001AQT4x | G156: 15 | H156: DENVER
A157: -OcN4z_w5d-HtdCImEyB | B157: Entertainment | Restaurant and Bar | C157: Entertainment|Bars | D157: Jake's Roadhouse | E157: CO | F157: 001OG000019lLOR | G157: 15 | H157: DENVER
A158: -Ocqbxj99WaFEDsmBHWs | B158: Entertainment | Restaurant and Bar | C158: Entertainment|Casual Dining | D158: Lazy Dog Restaurant & Bar - Garland | E158: TX | F158: 001OG00001A9SZo | H158: DALLAS - FT. WORTH
A159: -Ocqc15Eq3BT-LtKoOQN | B159: Entertainment | Restaurant and Bar | C159: Entertainment|Casual Dining | D159: Lazy Dog Restaurant & Bar - Irvine | E159: CA | F159: 001OG00001A9SZ9 | H159: LOS ANGELES
A160: -Ocqct_BL-gJL0R8qTZI | B160: Entertainment | Restaurant and Bar | C160: Entertainment|Casual Dining | D160: Lazy Dog Restaurants H/O | E160: CA | F160: 001OG000018mdrb | H160: LOS ANGELES
A161: -OcqmKTOhLz_P2u0HNPG | B161: Entertainment | Restaurant and Bar | C161: Entertainment|Casual Dining | D161: Captain's Sports Lounge Head Office | E161: MO | F161: 001OG00001BRycN | H161: KANSAS CITY
A162: -OcqYeTVgDap5iy5jxiU | B162: Entertainment | Restaurant and Bar | C162: Entertainment|Casual Dining | D162: The Post Sports Bar & Grill - Fenton | E162: MO | F162: 001OG00001AGdLH | G162: 15 | H162: ST. LOUIS
A163: -OcrG3SzXP1YJCEs4ho_ | B163: Entertainment | Restaurant and Bar | C163: Entertainment|Casual Dining | D163: TBirds | E163: CO | F163: 001OG000019lM9w | G163: 15 | H163: DENVER
A164: -Ocw0yTWvChpA9cwKO9m | B164: Entertainment | Restaurant and Bar | C164: Entertainment|Bars | D164: Woody's Pub & Grub | E164: MO | F164: 001OG000019lB3H | G164: 15 | H164: COLUMBIA - JEFFERSON CITY
A165: -Od9iiogiyEyLwlosMbQ | B165: Entertainment | Restaurant and Bar | C165: Entertainment|Bars | D165: The Bar Mission | E165: KS | F165: 001OG000019lKbL | G165: 15 | H165: KANSAS CITY
A166: -Od9u2AOs6A15a_8kbAp | B166: Entertainment | Restaurant and Bar | C166: Entertainment|Casual Dining | D166: The Sink | E166: CO | F166: 001OG000019lLB8 | G166: 15 | H166: DENVER
A167: -OdAv9NU7PtQG3ZEQIxc | B167: Entertainment | Restaurant and Bar | C167: Entertainment|Casual Dining | D167: HopCat - Partridge Creek | E167: MI | F167: 001OG0000193rdB | G167: 15 | H167: DETROIT
A168: -OdAw0RPZ4Ar4zY5KSlQ | B168: Entertainment | Restaurant and Bar | C168: Entertainment|Casual Dining | D168: HopCat - Royal Oak | E168: MI | F168: 001OG00000uxK4w | G168: 15 | H168: DETROIT
A169: -OdAwb040ZR5cyFCIRZp | B169: Entertainment | Restaurant and Bar | C169: Entertainment|Casual Dining | D169: HopCat - Livonia | E169: MI | F169: 001OG00000uxK5N | G169: 15 | H169: DETROIT
A170: -OdAWhhouCAWXdEyz_Rm | B170: Entertainment | Restaurant and Bar | C170: Entertainment|Casual Dining | D170: Guthrie's Sports Bar & Grill | E170: CO | F170: 001OG000019lL9n | G170: 15 | H170: COLORADO SPRINGS - PUEBLO
A171: -OdEuE098AfX7QPCt0AM | B171: Entertainment | Restaurant and Bar | C171: Entertainment|Casual Dining | D171: KJ's Bar & Grill | E171: MO | F171: 001OG00001AGch8 | G171: 15 | H171: ST. LOUIS
A172: -OdFfwaC7v9f2Gs6RADN | B172: Entertainment | Restaurant and Bar | C172: Entertainment|Casual Dining | D172: Capital Ale House - Harrisonburg | E172: VA | F172: 001OG000017Lye9 | G172: 15 | H172: HARRISONBURG
A173: -OdFh0QrcL4IGLGpuNwQ | B173: Entertainment | Restaurant and Bar | C173: Entertainment|Casual Dining | D173: Capital Ale House - Fredericksburg | E173: VA | F173: 001OG000017Lr1b | G173: 15 | H173: WASHINGTON, DC (HAGRSTWN)
... A177: -OdjMdQ6E2q825Z8iZ-f | B177: Entertainment | Restaurant and Bar | C177: Entertainment|Casual Dining | D177: Hotshots Sports Bar & Grill - Charlotte | E177: NC | F177: 001OG00001Awswo | G177: 15 | H177: CHARLOTTE
A178: -OdjNlrLTEcXTScmioti | B178: Entertainment | Restaurant and Bar | C178: Entertainment|Bars | D178: Gibson's Restaurant Group - HO | E178: IL | F178: 001OG00001C1rpF | H178: CHICAGO
A179: -OdjtsqI-SHxW8w4Law2 | B179: Entertainment | Restaurant and Bar | C179: Entertainment|Casual Dining | D179: Fallon's Grill and Tap | E179: MO | F179: 001OG00001AGcUd | G179: 15 | H179: ST. LOUIS
A180: -OdjU_ttvOIS4l5BT-0Y | B180: Entertainment | Restaurant and Bar | C180: Entertainment|Casual Dining | D180: Dog Prairie Tavern | E180: MO | F180: 001OG00001AGcN3 | G180: 15 | H180: ST. LOUIS
A181: -OdJyHhF2EqJhnDaee7B | B181: Entertainment | Restaurant and Bar | C181: Entertainment|Bars | D181: The Hideout Bar & Grill | E181: MO | F181: 001OG000019lB2q | G181: 15 | H181: KANSAS CITY
A182: -OdjZYXyInJSUJNyYFtR | B182: Entertainment | Restaurant and Bar | C182: Entertainment|Casual Dining | D182: Citgo Food Mart -3801 Old Hwy 41 | E182: GA | F182: 001OG00001BpEOg | G182: 15 | H182: ATLANTA
A183: -OdK1VintmpspU9N7WXO | B183: Entertainment | Restaurant and Bar | C183: Entertainment|Casual Dining | D183: Teresa's | Mexican Restaurant - Maple Grove | E183: MN | F183: 001OG000019z4gv | G183: 15 | H183: MINNEAPOLIS - ST. PAUL
A184: -OdKE6yQU1TBlweKKJxV | B184: Entertainment | Restaurant and Bar | C184: Entertainment|Casual Dining | D184: A Bit Twisted Brewery & BBQ | E184: CO | F184: 001OG00001BGSxa | G184: 15 | H184: DENVER
A185: -OdKjIhTbaqTTs5OwxWP | B185: Entertainment | Restaurant and Bar | C185: Entertainment|Casual Dining | D185: Blue Door Pub - University | E185: MN | F185: 001OG00001647VV | G185: 15 | H185: MINNEAPOLIS - ST. PAUL
A186: -OdKlYJpuD57Mlne8gR8 | B186: Entertainment | Restaurant and Bar | C186: Entertainment|Casual Dining | D186: Blue Door Pub - Longfellow | E186: MN | F186: 001OG00001647ha | G186: 15 | H186: MINNEAPOLIS - ST. PAUL
A187: -OdKqTHJzKi0Osgs2djH | B187: Entertainment | Restaurant and Bar | C187: Entertainment|Casual Dining | D187: Boardwalk Billy's Raw Bar and Ribs - Keynes | E187: NC | F187: 001OG00001AwtxO | G187: 15 | H187: CHARLOTTE
A188: -ODlePPK_m2Ijri2lHdx | B188: Entertainment | Restaurant and Bar | C188: Entertainment|Casual Dining | D188: Wolfies | E188: TX | F188: 0018V00002gQoUn | G188: 15 | H188: HOUSTON
A189: -ODmU_LXOM-oqB1h-j_J | B189: Entertainment | Restaurant and Bar | C189: Entertainment|Casual Dining | D189: 301 Plaza Restaurant (921 Middletown Warwick Rd) | E189: DE | F189: 001OG00000mjXjp | H189: PHILADELPHIA
A190: -OdPok5eHlDwTQoedckK | B190: Entertainment | Restaurant and Bar | C190: Entertainment|Casual Dining | D190: Parrot's Sports Grill | E190: CO | F190: 001OG000019lIjS | G190: 15 | H190: DENVER
A191: -OdPrCHPOtaS40vtAEES | B191: Entertainment | Restaurant and Bar | C191: Entertainment|Casual Dining | D191: Bitter Tom's Distillery | E191: MI | F191: 001OG00001BFOuT | G191: 15 | H191: DETROIT
A192: -OdQAhkSFZZVuyCVMfKZ | B192: Entertainment | Restaurant and Bar | C192: Entertainment|Casual Dining | D192: Fenns's Grocery | E192: MS | F192: 001OG00001BVY3V | G192: 15 | H192: JACKSON, MS
A193: -OdQDFh8GkJkt6QM_1uX | B193: Entertainment | Restaurant and Bar | C193: Entertainment|Bars | D193: The Combine | E193: MO | F193: 001OG000019lKau | G193: 15 | H193: KANSAS CITY
A194: -ODrTuggsMpZHRzpIehp | B194: Entertainment | Restaurant and Bar | C194: Entertainment|Casual Dining | D194: HOMETOWN SPORTS BAR & GRILL | E194: TX | F194: 0018V00002gQmmt | G194: 15 | H194: HOUSTON
A195: -OdsrhZAjDR7JDx-PI4C | B195: Entertainment | Restaurant and Bar | C195: Entertainment|Casual Dining | D195: Flat Iron Cafe | E195: OH | F195: 001OG00001AwsE6 | G195: 15 | H195: CLEVELAND - AKRON (CANTON)
A196: -OdszORGKhcsTe-oPYnI | B196: Entertainment | Restaurant and Bar | C196: Entertainment|Casual Dining | D196: Capital Ale House - Richmond | E196: VA | F196: 001OG000017LsiQ | G196: 15 | H196: RICHMOND - PETERSBURG
A197: -OdsztACfcC9OE4qj3wE | B197: Entertainment | Restaurant and Bar | C197: Entertainment|Casual Dining | D197: Capital Ale House - Midlothian | E197: VA | F197: 001OG000017Ln1s | G197: 15 | H197: RICHMOND - PETERSBURG
A198: -Odt6YxUAwc96VWJ9VCl | B198: Entertainment | Restaurant and Bar | C198: Entertainment|Casual Dining | D198: East End Bistro & Pub | E198: OH | F198: 001OG00001AwqBl | G198: 15 | H198: CLEVELAND - AKRON (CANTON)
A199: -OdtQF49l8SPEdhEFVLM | B199: Entertainment | Restaurant and Bar | C199: Entertainment|Bars | D199: BB's Grill | E199: KS | F199: 001OG000019lKR7 | G199: 15 | H199: KANSAS CITY
A200: -OdtxS_dMOf5XK1SrLzy | B200: Entertainment | Restaurant and Bar | C200: Entertainment|Casual Dining | D200: Hamlin Pub - ST. CLAIR | E200: MI | F200: 001OG000015Xzh2 | G200: 15 | H200: DETROIT
A201: -Odu2Ia0rHkSZ45Osg82 | B201: Entertainment | Restaurant and Bar | C201: Entertainment|Casual Dining | D201: Sports Lounge Off Broadway | E201: CO | F201: 001OG000019lM5A | G201: 15 | H201: DENVER
... A244: -OecOQMGKQy9Mu_eVOHk | B244: Entertainment | Restaurant and Bar | C244: Entertainment|Casual Dining | D244: Big Al's Pub & Grubberia | E244: NC | F244: 001OG00001AwtOP | G244: 15 | H244: CHARLOTTE
A245: -OEG2szZunuxP1fikTQ0 | B245: Entertainment | Restaurant and Bar | C245: Entertainment|Casual Dining | D245: Bombshells Corporate Head Office | E245: TX | F245: 001OG00000nUKuk | H245: HOUSTON
A246: -OeHtiBU375nCF7xSteR | B246: Entertainment | Restaurant and Bar | C246: Entertainment|Casual Dining | D246: Steamers Sports Pub | E246: NC | F246: 001OG00001Awtjn | H246: CHARLOTTE
A247: -OeIeTq37gg3I7tFthnq | B247: Entertainment | Restaurant and Bar | C247: Entertainment|Bars | D247: El Plato Mexican Grill & Cantina | E247: MO | F247: 001OG000019lKR9 | G247: 15 | H247: KANSAS CITY
A248: -OeIiNjZlnpP3stvY99U | B248: Entertainment | Restaurant and Bar | C248: Entertainment|Casual Dining | D248: King Grill | E248: MO | F248: 001OG00001AGcgq | G248: 15 | H248: ST. LOUIS
A249: -OeIn6ZbAshBUn7tYMUQ | B249: Entertainment | Restaurant and Bar | C249: Entertainment|Casual Dining | D249: Spoto's Bar and Grill | E249: OH | F249: 001OG00001Awq8m | G249: 15 | H249: CLEVELAND - AKRON (CANTON)
A250: -OeIqpeY-CkbtWY2aVzk | B250: Entertainment | Restaurant and Bar | C250: Entertainment|Casual Dining | D250: Ray's SportsHouse | E250: MO | F250: 001OG00001AGcy7 | G250: 15 | H250: ST. LOUIS
A251: -OeItuvNv7pbUXbDzbmh | B251: Entertainment | Restaurant and Bar | C251: Entertainment|Casual Dining | D251: Nowhere Bar & Grill | E251: CA | F251: 001OG000010cA6O | G251: 15 | H251: SAN FRANCISCO - OAK - SAN JOSE
A252: -OELWRLmGf6kWZIdiK8M | B252: Entertainment | Restaurant and Bar | C252: Entertainment|Casual Dining | D252: Pablo's Cantina Mexican Grill (Old Location) | E252: TX | F252: 001OG00000mDtxW | G252: 15 | H252: HOUSTON
A253: -OeMbr-4LyXj245qu5jd | B253: Entertainment | Restaurant and Bar | C253: Entertainment|Casual Dining | D253: The Brass Tap - Richmond | E253: VA | F253: 001OG00000kxJFS | G253: 15 | H253: RICHMOND - PETERSBURG
A254: -OeMsO7bZal5mTDQDMk7 | B254: Entertainment | Restaurant and Bar | C254: Entertainment|Bars | D254: Streetcar Grille & Tavern KC Northland | E254: MO | F254: 001OG000019lKlJ | G254: 15 | H254: KANSAS CITY
A255: -OeMt5HoAp-1ROjYYH3q | B255: Entertainment | Restaurant and Bar | C255: Entertainment|Casual Dining | D255: Cozumel | E255: OH | F255: 001OG00001CIiPl | G255: 15 | H255: CLEVELAND - AKRON (CANTON)
A256: -OeMt6YXAWWefIgCPBtC | B256: Entertainment | Restaurant and Bar | C256: Entertainment|Bars | D256: Streetcar Grille & Tavern Downtown Kansas City | E256: MO | F256: 001OG000019l7y7 | G256: 15 | H256: KANSAS CITY
A257: -OeMwf1SVp6R9rdV3KA0 | B257: Entertainment | Restaurant and Bar | C257: Entertainment|Casual Dining | D257: El Patron | E257: OH | F257: 001OG00001CIiuP | G257: 15 | H257: CLEVELAND - AKRON (CANTON)
A258: -OeNj3uYjrLml-nq4aTB | B258: Entertainment | Restaurant and Bar | C258: Entertainment|Casual Dining | D258: Sauced Taproom & Kitchen | E258: OH | F258: 001OG00001Awq2R | G258: 15 | H258: CLEVELAND - AKRON (CANTON)
... A322: -OJ3zvGWcHIuCV3KUyA- | B322: Entertainment | Restaurant and Bar | C322: Entertainment|Casual Dining | D322: O'Brien's | E322: CA | F322: 001OG00000OYpMv | G322: 15 | H322: SAN DIEGO
A323: -OJ44XqE6S_Q9qu1fyV5 | B323: Entertainment | Restaurant and Bar | C323: Entertainment|Bars | D323: Kava Colorado | E323: CO | F323: 001OG00000jGWJw | H323: COLORADO SPRINGS - PUEBLO
A324: -OJ5XAnFwo2eI0xGNI-F | B324: Entertainment | Restaurant and Bar | C324: Entertainment|Bars | D324: Little Woodrow?s - Lubbock | E324: TX | F324: 001OG00000ry3hL | G324: 15 | H324: LUBBOCK
A325: -OJ5XKAdJtpxI1nflE3E | B325: Entertainment | Restaurant and Bar | C325: Entertainment|Bars | D325: Little Woodrow?s - Midland | E325: TX | F325: 001OG00000ryA2o | G325: 15 | H325: ODESSA - MIDLAND
A326: -OJeWxTK__c1vad5L20m | B326: Entertainment | Restaurant and Bar | C326: Entertainment|Casual Dining | D326: The Draft Restaurant and Sports Bar | E326: CA | F326: 001OG00000q4eYk | G326: 15 | H326: SAN DIEGO
A327: -OJPo573jcRAGSbaLZgN | B327: Entertainment | Restaurant and Bar | C327: Entertainment|Casual Dining | D327: Play By Play Sports Bar and Grill | E327: FL | F327: 001OG00000vOhnm | G327: 15 | H327: MIAMI - FT. LAUDERDALE
...
