Workbook

Sheet State Level Data
A1: state | B1: impressions | C1: spend
A2: TX | B2: 1293090.6 | C2: 6857.52
A3: AL, DE, OK, SC, SD, ID, WA, WI | B3: 796695 | C3: 2105.22
A4: FL | B4: 1435934.1 | C4: 11979.65
A5: GA | B5: 545368.77 | C5: 5697.19
A6: DC | B6: 30410.45 | C6: 394.64
A7: CA | B7: 320750.89 | C7: 2965.78
A8: total | B8: =SUM(B2:B7) -> 4422249.8 | C8: =SUM(C2:C7) -> 30000

Sheet Spend By Day
A1: date | B1: impressions | C1: spend
A2: 45778 | B2: 417064.58 | C2: 967.742
A3: 45779 | B3: 369149.27 | C3: 967.742
A4: 45780 | B4: 491559.62 | C4: 967.742
A5: 45781 | B5: 568654.74 | C5: 967.742
A6: 45782 | B6: 273861.89 | C6: 967.742
A7: 45783 | B7: 83816.725 | C7: 967.742
A8: 45784 | B8: 83025.595 | C8: 967.742
A9: 45785 | B9: 89000.865 | C9: 967.742
A10: 45786 | B10: 85787.676 | C10: 967.742
A11: 45787 | B11: 140691.94 | C11: 967.742
A12: 45788 | B12: 121159.57 | C12: 967.742
A13: 45789 | B13: 80665.023 | C13: 967.742
... A32: 45808 | B32: 101139.39 | C32: 967.742
A33: total | B33: =SUM(B2:B32) -> 4422249.8 | C33: =SUM(C2:C32) -> 30000.002

Sheet Venue Level Data
A1: clientId | B1: venue | C1: venue type | D1: market | E1: state | F1: lat | G1: long | H1: impressions | I1: ScreensAtLocation
A2: -OB7UCQznmkg1Lpr3VVq | B2: Marathon, 1283 Center Point Pkwy, Birmingham, AL | C2: =VLOOKUP(A2,salesforce!A:E, 3, FALSE) -> Retail|Convenience Stores | D2: Other | E2: =VLOOKUP(A2,salesforce!A:E, 5, FALSE) -> AL | F2: 33.619051 | G2: -86.68437 | H2: 6280.56 | I2: 2
A3: -OJ-lxPLKceu7e03c5dN | B3: King Vape & Tobacco | C3: =VLOOKUP(A3,salesforce!A:E, 3, FALSE) -> Retail|Dispensaries | D3: Other | E3: =VLOOKUP(A3,salesforce!A:E, 5, FALSE) -> AL | F3: 33.168333 | G3: -86.250233 | H3: 11508.37 | I3: 1
A4: -OJ0VXhsG8Zcm2JZNPda | B4: Millbrook Chevron | C4: =VLOOKUP(A4,salesforce!A:E, 3, FALSE) -> Retail|Convenience Stores | D4: Other | E4: =VLOOKUP(A4,salesforce!A:E, 5, FALSE) -> AL | F4: 32.477272 | G4: -86.361017 | H4: 4538.25 | I4: 1
A5: -Nj9CrKjfOKPCZ-c_KEW | B5: 90 West Lounge | C5: =VLOOKUP(A5,salesforce!A:E, 3, FALSE) -> Entertainment|Bars | D5: Los Angeles | E5: =VLOOKUP(A5,salesforce!A:E, 5, FALSE) -> CA | F5: 33.985282 | G5: -118.42471 | H5: 27915.153 | I5: 5
A6: -O25LWFCwMaMybdiDFOL | B6: SD TapRoom | C6: =VLOOKUP(A6,salesforce!A:E, 3, FALSE) -> Entertainment|Casual Dining | D6: San Diego | E6: =VLOOKUP(A6,salesforce!A:E, 5, FALSE) -> CA | F6: 32.798307 | G6: -117.24671 | H6: 2147.3194 | I6: 16
A7: -O3-9vFfUfp34D7Dwrfe | B7: Knotty Barrel Rancho Penasquitos | C7: =VLOOKUP(A7,salesforce!A:E, 3, FALSE) -> Entertainment|Casual Dining | D7: San Diego | E7: =VLOOKUP(A7,salesforce!A:E, 5, FALSE) -> CA | F7: 32.957793 | G7: -117.12631 | H7: 5923.0228 | I7: 8
A8: -O4gCxDrYuvV7sXd5Btz | B8: Guava Beach Bar & Grill | C8: =VLOOKUP(A8,salesforce!A:E, 3, FALSE) -> Entertainment|Casual Dining | D8: San Diego | E8: =VLOOKUP(A8,salesforce!A:E, 5, FALSE) -> CA | F8: 32.782926 | G8: -117.25275 | H8: 2684.1493 | I8: 3
A9: -O5F9mMme1oRI-zpMAgM | B9: Ojos Locos Sports Cantina - Lynwood | C9: =VLOOKUP(A9,salesforce!A:E, 3, FALSE) -> Entertainment|Bars | D9: Los Angeles | E9: =VLOOKUP(A9,salesforce!A:E, 5, FALSE) -> CA | F9: 33.928476 | G9: -118.21481 | H9: 4294.6389 | I9: 43
A10: -O5UAEMmHqgG91qkc51U | B10: Ojos Locos Sports Cantina - Downey | C10: =VLOOKUP(A10,salesforce!A:E, 3, FALSE) -> Entertainment|Bars | D10: Los Angeles | E10: =VLOOKUP(A10,salesforce!A:E, 5, FALSE) -> CA | F10: 33.938879 | G10: -118.13199 | H10: 6370.381 | I10: 42
A11: -O5UmgRMlYALl3cy9gg4 | B11: Players Sports Grill - Kearny Villa | C11: =VLOOKUP(A11,salesforce!A:E, 3, FALSE) -> Entertainment|Bars | D11: San Diego | E11: =VLOOKUP(A11,salesforce!A:E, 5, FALSE) -> CA | F11: 32.829349 | G11: -117.14079 | H11: 6419.1131 | I11: 6
A12: -O5Uo3r9Fvz0FX61Wvmh | B12: Players Sports Grill - Poway | C12: =VLOOKUP(A12,salesforce!A:E, 3, FALSE) -> Entertainment|Casual Dining | D12: San Diego | E12: =VLOOKUP(A12,salesforce!A:E, 5, FALSE) -> CA | F12: 32.959547 | G12: -117.04026 | H12: 5189.3553 | I12: 5
A13: -O5UxVlCyO7vG8McNdyE | B13: TapRoom Beer Company | C13: =VLOOKUP(A13,salesforce!A:E, 3, FALSE) -> Entertainment|Bars | D13: San Diego | E13: =VLOOKUP(A13,salesforce!A:E, 5, FALSE) -> CA | F13: 32.755524 | G13: -117.14357 | H13: 2147.3194 | I13: 12
... A299: -O4uOfYBLjujwxlgy8zo | B299: HerbRX - Spring Green | C299: =VLOOKUP(A299,salesforce!A:E, 3, FALSE) -> Retail|Dispensaries | D299: Other | E299: =VLOOKUP(A299,salesforce!A:E, 5, FALSE) -> WI | F299: 43.176589 | G299: -90.067159 | H299: 3170 | I299: 1

Sheet Creative Level Data
A1: slideId | B1: slideName | C1: imageName | D1: impressions
A2: -OMI8OK2QgCsqrhUi_X2 | B2: BetOnline March Madness Sweet 16 Slideshow.mp4 | C2: 1743004205111-BetOnline March Madness Sweet 16 Slideshow.mp4 | D2: 408285.82
A3: -OMI8PaNTPKbBySI56wv | B3: BetOnline March Madness Sweet 16 Static.mp4 | C3: 1743004210731-BetOnline March Madness Sweet 16 Static.mp4 | D3: 253672.5
A4: -OMwVo40P8yjuG_9_ms1 | B4: BetOnline Ad 4:3 - 4:7.mp4 | C4: 1743698203318-BetOnline Ad 4:3 - 4:7.mp4 | D4: 1444.4358
A5: -OOAxchMlAIZZ2RQHFqn | B5: betonline_shorts_stanley_cup_playoffs_041725(old).mp4 | C5: 1745031166420-betonline_shorts_stanley_cup_playoffs_041725.mp4 | D5: 235860.58
A6: -OOAxglwlktx-LeznIEu | B6: betonline_shorts_nba_playoffs_041725(old).mp4 | C6: 1745031190750-betonline_shorts_nba_playoffs_041725.mp4 | D6: 198967.21
A7: -OOTKfIJ5U2fjHWc0eRP | B7: BetOnline Creative - 30 Sec Static.mp4 | C7: 1745339478981-BetOnline Creative - 30 Sec Static.mp4 | D7: 1225518.6
A8: -OOTKvyJ3UNtTH0V53xZ | B8: BetOnline Creative.mp4 | C8: 1745339486172-BetOnline Creative.mp4 | D8: 436288.47
A9: -OOYdEkJMC2IMTCHyyAC | B9: BetOnline Creative (1).mp4 | C9: 1745428360222-BetOnline Creative (1).mp4 | D9: 1269319.1
A10: -OP2YXJGXJLEtm-hY5Ro | B10: BetOnline Ad - Kentucky Derby (until 5:4).mp4 | C10: 1745963831774-BetOnline Ad - Kentucky Derby (until 5:4).mp4 | D10: 7518.7945
A11: -OPCpBCOClwJZWdNJIuN | B11: BetOnline Ad - Derby Short (until 54).mp4 | C11: 1746136196158-BetOnline Ad - Derby Short (until 54).mp4 | D11: 5944.2072
A12: -OPHn9lq-VES1KIBYgaN | B12: BetOnline Creative Kentucky Derby (until 54).mp4 | C12: 1746219600859-BetOnline Creative Kentucky Derby (until 54).mp4 | D12: 4816.4389
A13: -OQiocsDzziQMnrVnylH | B13: BetOnline NBA Creative.mp4 | C13: 1747763289561-BetOnline NBA Creative.mp4 | D13: 347804.6
A14: -ORX5k8orTQph8kUpHww | B14: BetOnline French Open Tennis Ad.mp4 | C14: 1748623879436-BetOnline French Open Tennis Ad.mp4 | D14: 26809.025
A15: total | D15: =SUM(D2:D14) -> 4422249.8

Sheet salesforce
A1: Firebase Id | B1: IAB Venue Type | C1: Vistar Venue Type | D1: Account Name | E1: Shipping State/Province
A2: -N7vB4glPqShJ1qEHZau | B2: Entertainment | Restaurant and Bar | C2: Entertainment|Bars | D2: Taiv HQ | E2: TX
A3: -O9M57k5rIUKvFdpgX4O | B3: Entertainment | Restaurant and Bar | C3: Entertainment|Casual Dining | D3: Horus Cafe | E3: NY
A4: -O9WJ2SlG98VV_CKfYaP | B4: Entertainment | Restaurant and Bar | C4: Entertainment|Casual Dining | D4: Shotzee's Bar And Grill | E4: TX
A5: -ODhIzSsJfxw9vskroUC | B5: Entertainment | Restaurant and Bar | C5: Entertainment|Casual Dining | D5: Carriage House Restaurant & Pub | E5: PA
A6: -ODlePPK_m2Ijri2lHdx | B6: Entertainment | Restaurant and Bar | C6: Entertainment|Casual Dining | D6: Wolfies | E6: TX
A7: -ODmU_LXOM-oqB1h-j_J | B7: Entertainment | Restaurant and Bar | C7: Entertainment|Casual Dining | D7: 301 Plaza Restaurant (921 Middletown Warwick Rd) | E7: DE
A8: -ODrTuggsMpZHRzpIehp | B8: Entertainment | Restaurant and Bar | C8: Entertainment|Casual Dining | D8: HOMETOWN SPORTS BAR & GRILL | E8: TX
A9: -OEG2szZunuxP1fikTQ0 | B9: Entertainment | Restaurant and Bar | C9: Entertainment|Casual Dining | D9: Bombshells Corporate Head Office | E9: TX
A10: -OELWRLmGf6kWZIdiK8M | B10: Entertainment | Restaurant and Bar | C10: Entertainment|Casual Dining | D10: Pablo's Cantina Mexican Grill (Old Location) | E10: TX
A11: -OEPu_3Zzy9Yieo-LD_3 | B11: Entertainment | Restaurant and Bar | C11: Entertainment|Casual Dining | D11: FW Thunderbird | E11: TX
A12: -OFigYv6WSwKmjm5pAoL | B12: Entertainment | Restaurant and Bar | C12: Entertainment|Casual Dining | D12: Just 1 Saloon | E12: TX
... A2648: -N-ZKIQhE4_at0latHj8 | B2648: Health & Beauty | Gyms | C2648: Health and Beauty|Gyms | D2648: Eli's Fitness Studio | E2648: FL
